safe_assert/__init__.py
safe_assert/py.typed
safe_assert-0.5.0.dist-info/LICENSE
safe_assert-0.5.0.dist-info/METADATA
safe_assert-0.5.0.dist-info/WHEEL
safe_assert-0.5.0.dist-info/RECORD
