Metadata-Version: 2.1
Name: safe-assert
Version: 0.5.0
Summary: Safe assert for Python that can be used together with optimised mode
Home-page: https://github.com/wemake-services/safe-assert
License: MIT
Keywords: assert,utility,helper,optimized mode
Author: sobolevn
Author-email: mail@sobolevn.me
Requires-Python: >=3.9,<4.0
Classifier: Development Status :: 4 - Beta
Classifier: Intended Audience :: Developers
Classifier: License :: OSI Approved :: MIT License
Classifier: Operating System :: OS Independent
Classifier: Programming Language :: Python :: 3
Classifier: Programming Language :: Python :: 3.9
Classifier: Programming Language :: Python :: 3.10
Classifier: Programming Language :: Python :: 3.11
Classifier: Programming Language :: Python :: 3.12
Classifier: Topic :: Software Development :: Libraries :: Python Modules
Classifier: Topic :: Utilities
Classifier: Typing :: Typed
Project-URL: Funding, https://github.com/sponsors/wemake-services
Project-URL: Repository, https://github.com/wemake-services/safe-assert
